README.md
setup.py
docums_encryptcontent_plugin.egg-info/PKG-INFO
docums_encryptcontent_plugin.egg-info/SOURCES.txt
docums_encryptcontent_plugin.egg-info/dependency_links.txt
docums_encryptcontent_plugin.egg-info/entry_points.txt
docums_encryptcontent_plugin.egg-info/requires.txt
docums_encryptcontent_plugin.egg-info/top_level.txt
encryptcontent/__init__.py
encryptcontent/plugin.py