Metadata-Version: 2.1
Name: docums-encryptcontent-plugin
Version: 2.0.1
Summary: A Docums plugin that encrypt/decrypt markdown content with AES
Home-page: https://github.com/khanhduy1407/docums-encryptcontent-plugin/
Author: NKDuy
Author-email: kn145660@gmail.com
License: MIT
Keywords: docums python markdown encrypt decrypt content
Platform: UNKNOWN
Classifier: Development Status :: 5 - Production/Stable
Classifier: Intended Audience :: Developers
Classifier: Intended Audience :: Information Technology
Classifier: License :: OSI Approved :: MIT License
Classifier: Programming Language :: Python
Classifier: Programming Language :: Python :: 3.5
Classifier: Programming Language :: Python :: 3.6
Classifier: Programming Language :: Python :: 3.7
Classifier: Programming Language :: Python :: 3.8
Classifier: Programming Language :: Python :: 3.9
Requires-Python: >=3.5
